[{"a":"컴파일 시작: test","b":1,"c":"2025/06/20 21:03:13 "},{"a":"컴파일 하였습니다: test","b":1,"c":"2025/06/20 21:03:13 "},{"a":"컴파일 시작: test","b":1,"c":"2025/06/20 21:03:13 "},{"a":"컴파일 하였습니다: test","b":1,"c":"2025/06/20 21:03:13 "},{"a":"컴파일 시작: 테스트봇","b":1,"c":"2025/06/20 21:04:51 "},{"a":"컴파일 하였습니다: 테스트봇","b":1,"c":"2025/06/20 21:04:51 "},{"a":"컴파일 시작: 테스트봇","b":1,"c":"2025/06/20 21:05:16 "},{"a":"컴파일 하였습니다: 테스트봇","b":1,"c":"2025/06/20 21:05:16 "},{"a":"컴파일 시작: 테스트봇","b":1,"c":"2025/06/20 21:05:42 "},{"a":"컴파일 하였습니다: 테스트봇","b":1,"c":"2025/06/20 21:05:42 "},{"a":"컴파일 시작: 테스트봇","b":1,"c":"2025/06/20 21:06:07 "},{"a":"컴파일 하였습니다: 테스트봇","b":1,"c":"2025/06/20 21:06:07 "},{"a":"컴파일 시작: 테스트봇","b":1,"c":"2025/06/20 21:06:07 "},{"a":"컴파일 하였습니다: 테스트봇","b":1,"c":"2025/06/20 21:06:07 "},{"a":"컴파일 시작: 테스트봇","b":1,"c":"2025/06/20 21:07:09 "},{"a":"컴파일 하였습니다: 테스트봇","b":1,"c":"2025/06/20 21:07:09 "},{"a":"컴파일 시작: 테스트봇","b":1,"c":"2025/06/20 21:07:09 "},{"a":"컴파일 하였습니다: 테스트봇","b":1,"c":"2025/06/20 21:07:09 "},{"a":"컴파일 시작: 테스트봇","b":1,"c":"2025/06/20 21:07:09 "},{"a":"컴파일 하였습니다: 테스트봇","b":1,"c":"2025/06/20 21:07:09 "},{"a":"컴파일 시작: 테스트봇","b":1,"c":"2025/06/20 21:07:09 "},{"a":"컴파일 하였습니다: 테스트봇","b":1,"c":"2025/06/20 21:07:09 "},{"a":"컴파일 시작: 테스트봇","b":1,"c":"2025/06/20 21:08:27 "},{"a":"컴파일 하였습니다: 테스트봇","b":1,"c":"2025/06/20 21:08:27 "},{"a":"컴파일 시작: 테스트봇","b":1,"c":"2025/06/20 21:08:27 "},{"a":"컴파일 하였습니다: 테스트봇","b":1,"c":"2025/06/20 21:08:27 "},{"a":"컴파일 시작: 테스트봇","b":1,"c":"2025/06/20 21:08:28 "},{"a":"컴파일 하였습니다: 테스트봇","b":1,"c":"2025/06/20 21:08:28 "},{"a":"컴파일 시작: 테스트봇","b":1,"c":"2025/06/20 21:09:34 "},{"a":"컴파일 하였습니다: 테스트봇","b":1,"c":"2025/06/20 21:09:34 "}]